cirrus/lib/__init__.py
cirrus/lib/errors.py
cirrus/lib/logging.py
cirrus/lib/process_payload.py
cirrus/lib/statedb.py
cirrus/lib/transfer.py
cirrus/lib/utils.py
cirrus_lib-0.8.1.dist-info/LICENSE
cirrus_lib-0.8.1.dist-info/METADATA
cirrus_lib-0.8.1.dist-info/WHEEL
cirrus_lib-0.8.1.dist-info/dependency_links.txt
cirrus_lib-0.8.1.dist-info/top_level.txt
cirrus_lib-0.8.1.dist-info/RECORD
