Metadata-Version: 2.1
Name: cirrus-lib
Version: 0.8.1
Summary: Cirrus Library
Home-page: https://github.com/cirrus-geo/cirrus-lib.git
Author: Matthew Hanson (matthewhanson), Element 84
License: Apache-2.0
Classifier: Intended Audience :: Developers
Classifier: License :: OSI Approved :: Apache Software License
Classifier: Programming Language :: Python :: 3.7
Classifier: Programming Language :: Python :: 3.8
Classifier: Programming Language :: Python :: 3.9
Classifier: Programming Language :: Python :: 3.10
License-File: LICENSE
Requires-Dist: boto3-utils (>=0.3.3)
Requires-Dist: requests (>=2.24.0)
Requires-Dist: python-json-logger (~=2.0)
Requires-Dist: jsonpath-ng (~=1.5.3)
